setup.py
scdnn/__init__.py
scdnn.egg-info/PKG-INFO
scdnn.egg-info/SOURCES.txt
scdnn.egg-info/dependency_links.txt
scdnn.egg-info/not-zip-safe
scdnn.egg-info/top_level.txt