Metadata-Version: 1.0
Name: scdnn
Version: 0.1
Summary: A Package for sparse coding using DNNs
Home-page: https://github.com/Chunmun91/scdnn
Author: Chunmun91
Author-email: chunmun.mahapatra0@gmail.com
License: MIT
Platform: UNKNOWN
